{
  "alignment": "start",
  "animateLoading": true,
  "backgroundColor": "white",
  "borderColor": "#E0DEDE",
  "borderRadius": "0.375rem",
  "borderWidth": "1",
  "bottomRow": 54.400000000000006,
  "boxShadow": "{{appsmith.theme.boxShadow.appBoxShadow}}",
  "children": [
    {
      "bottomRow": 116.00000000000001,
      "canExtend": false,
      "containerStyle": "none",
      "detachFromLayout": true,
      "displayName": "Canvas",
      "dynamicBindingPathList": [],
      "flexLayers": [
        {
          "children": [
            {
              "align": "start",
              "id": "fn0akh5pq6"
            }
          ]
        },
        {
          "children": [
            {
              "align": "start",
              "id": "6b3l1yyh9c"
            }
          ]
        }
      ],
      "hideCard": true,
      "isDeprecated": false,
      "isLoading": false,
      "isVisible": true,
      "key": "dieduwxvap",
      "leftColumn": 0,
      "minHeight": 120,
      "parentColumnSpace": 1,
      "parentId": "58zhgx1sbx",
      "parentRowSpace": 1,
      "positioning": "vertical",
      "renderMode": "CANVAS",
      "responsiveBehavior": "fill",
      "rightColumn": 198.5625,
      "topRow": 0,
      "type": "CANVAS_WIDGET",
      "useAutoLayout": true,
      "version": 1,
      "widgetId": "s0qqwomrjm",
      "widgetName": "Canvas1Copy1"
    }
  ],
  "displayName": "Stats Box",
  "dynamicBindingPathList": [
    {
      "key": "boxShadow"
    }
  ],
  "dynamicHeight": "AUTO_HEIGHT",
  "dynamicTriggerPathList": [],
  "flexVerticalAlignment": "end",
  "hideCard": false,
  "iconSVG": "/static/media/icon.382a7c7bc55323fbbd8edd79208c5324.svg",
  "isCanvas": true,
  "isDeprecated": false,
  "isLoading": false,
  "isVisible": true,
  "key": "gsbsi84itj",
  "leftColumn": 0,
  "maxDynamicHeight": 9000,
  "minDynamicHeight": 14,
  "originalBottomRow": 40,
  "originalTopRow": 26,
  "parentColumnSpace": 16.546875,
  "parentId": "0",
  "parentRowSpace": 10,
  "renderMode": "CANVAS",
  "responsiveBehavior": "fill",
  "rightColumn": 64,
  "shouldScrollContents": true,
  "topRow": 42.800000000000004,
  "type": "STATBOX_WIDGET",
  "widgetId": "58zhgx1sbx",
  "widgetName": "StatRefundLastMonth"
}